{
	"type": "URL157",
	"children": [
		{"type": "title",
		"children": [
			"Eyeglasses"

		]},
		{"type": "heading",
		"children": [
			"In garbage"

		]},
		{"type": "para",
		"children": [
			"Eyeglasses can go in the garbage."

		]},
		{"type": "heading",
		"children": [
			"Drop-off locations"

		]},
		{"type": "para",
		"children": [
			"You can donate eyeglasses to ",
{"type": "link", "href": "http://www.lionsclubs.org/EN/our-work/sight-programs/eyeglass-recycling/how-you-can-help.php", "text": "The Lions Club"},
			" or organizations affiliated with ",
{"type": "link", "href": "https://onesight.org/faqs/", "text": "OneSight"},
			"."

		]}

	]}
